README.md
setup.py
rpc/__init__.py
rpc.synpase.astraea.egg-info/PKG-INFO
rpc.synpase.astraea.egg-info/SOURCES.txt
rpc.synpase.astraea.egg-info/dependency_links.txt
rpc.synpase.astraea.egg-info/requires.txt
rpc.synpase.astraea.egg-info/top_level.txt
rpc/synapse/__init__.py
rpc/synapse/astraea/__init__.py
rpc/synapse/astraea/event_client.py
rpc/synapse/astraea/event_server.py
rpc/synapse/astraea/rpc_client.py
rpc/synapse/astraea/rpc_server.py
rpc/synapse/astraea/synapse.py