Metadata-Version: 1.1
Name: rpc.synpase.astraea
Version: 1.4.3
Summary: A rpc framework base RabbitMQ
Home-page: https://github.com/synapse-rpc
Author: xrain0610
Author-email: xrain@simcu.com
License: BSD License
Platform: all
Classifier: Operating System :: OS Independent
Classifier: License :: OSI Approved :: BSD License
Classifier: Programming Language :: Python
Classifier: Programming Language :: Python :: Implementation
Classifier: Programming Language :: Python :: 2
Classifier: Programming Language :: Python :: 2.7
Classifier: Programming Language :: Python :: 3
Classifier: Programming Language :: Python :: 3.4
Classifier: Programming Language :: Python :: 3.5
Classifier: Programming Language :: Python :: 3.6
Classifier: Topic :: Software Development :: Libraries
